dataframes/__init__.py
dataframes/main.py
dataframes-0.2.dist-info/METADATA
dataframes-0.2.dist-info/WHEEL
dataframes-0.2.dist-info/top_level.txt
dataframes-0.2.dist-info/RECORD
