Metadata-Version: 2.2
Name: dataframes
Version: 0.2
Requires: pandas
Requires: numpy
Dynamic: description
Dynamic: requires
